Metadata-Version: 2.3
Name: django-plugin-browser-reload
Version: 0.1.1
Summary: Django plugin wrapping django-browser-reload
Author: Joel Sleppy
Author-email: Joel Sleppy <joel@sleppytech.com>
License: Apache-2.0
Classifier: License :: OSI Approved :: Apache Software License
Requires-Dist: django
Requires-Dist: djp>=0.3.1
Requires-Dist: django-browser-reload==1.*
